{
	"Version": 3,
	"Meta": {
		"Duration": 2.5,
		"Fps": 30.0,
		"Loop": true,
		"AreBeziersRestricted": true,
		"CurveCount": 18,
		"TotalSegmentCount": 31,
		"TotalPointCount": 103,
		"UserDataCount": 0,
		"TotalUserDataSize": 0
	},
	"Curves": [
		{
			"Target": "Model",
			"Id": "EyeBlink",
			"Segments": [
				0,
				1,
				1,
				0.056,
				1,
				0.111,
				0,
				0.167,
				0,
				1,
				0.222,
				0,
				0.278,
				1,
				0.333,
				1,
				1,
				1.056,
				1,
				1.778,
				1,
				2.5,
				1
			]
		},
		{
			"Target": "Parameter",
			"Id": "Param6",
			"Segments": [
				0,
				-30,
				0,
				2.5,
				-30
			]
		},
		{
			"Target": "Parameter",
			"Id": "Param8",
			"Segments": [
				0,
				-30,
				0,
				2.5,
				-30
			]
		},
		{
			"Target": "Parameter",
			"Id": "Param10",
			"Segments": [
				0,
				0,
				1,
				0.311,
				0,
				0.622,
				-15,
				0.933,
				-15,
				1,
				1.456,
				-15,
				1.978,
				0,
				2.5,
				0
			]
		},
		{
			"Target": "Parameter",
			"Id": "Param11",
			"Segments": [
				0,
				0,
				1,
				0.311,
				0,
				0.622,
				1,
				0.933,
				1,
				1,
				1.456,
				1,
				1.978,
				0,
				2.5,
				0
			]
		},
		{
			"Target": "Parameter",
			"Id": "Param13",
			"Segments": [
				0,
				0,
				1,
				0.311,
				0,
				0.622,
				-27,
				0.933,
				-27,
				1,
				1.456,
				-27,
				1.978,
				0,
				2.5,
				0
			]
		},
		{
			"Target": "Parameter",
			"Id": "Param14",
			"Segments": [
				0,
				0,
				1,
				0.311,
				0,
				0.622,
				-12,
				0.933,
				-12,
				1,
				1.456,
				-12,
				1.978,
				0,
				2.5,
				0
			]
		},
		{
			"Target": "Parameter",
			"Id": "Param16",
			"Segments": [
				0,
				0,
				1,
				0.311,
				0,
				0.622,
				-15,
				0.933,
				-15,
				1,
				1.456,
				-15,
				1.978,
				0,
				2.5,
				0
			]
		},
		{
			"Target": "Parameter",
			"Id": "Param17",
			"Segments": [
				0,
				0,
				1,
				0.311,
				0,
				0.622,
				-4,
				0.933,
				-4,
				1,
				1.456,
				-4,
				1.978,
				0,
				2.5,
				0
			]
		},
		{
			"Target": "Parameter",
			"Id": "ParamMouthForm",
			"Segments": [
				0,
				1,
				1,
				0.833,
				1,
				1.667,
				1,
				2.5,
				1
			]
		},
		{
			"Target": "Parameter",
			"Id": "ParamMouthOpenY",
			"Segments": [
				0,
				0.3,
				1,
				0.833,
				0.3,
				1.667,
				0.3,
				2.5,
				0.3
			]
		},
		{
			"Target": "Parameter",
			"Id": "ParamBreath",
			"Segments": [
				0,
				0,
				1,
				0.178,
				0,
				0.356,
				0.3,
				0.533,
				0.3,
				1,
				1.189,
				0.3,
				1.844,
				0,
				2.5,
				0
			]
		},
		{
			"Target": "Parameter",
			"Id": "Param_Angle_Rotation_1_ArtMesh",
			"Segments": [
				0,
				0,
				1,
				0.222,
				0,
				0.444,
				-3,
				0.667,
				-3,
				1,
				1.278,
				-3,
				1.889,
				0,
				2.5,
				0
			]
		},
		{
			"Target": "Parameter",
			"Id": "Param_Angle_Rotation_8_ArtMesh",
			"Segments": [
				0,
				0,
				1,
				0.222,
				0,
				0.444,
				-5,
				0.667,
				-5,
				1,
				1.278,
				-5,
				1.889,
				0,
				2.5,
				0
			]
		},
		{
			"Target": "Parameter",
			"Id": "Param_Angle_Rotation_9_ArtMesh",
			"Segments": [
				0,
				0,
				0,
				2.5,
				0
			]
		},
		{
			"Target": "Parameter",
			"Id": "Param_Angle_Rotation_10_ArtMesh",
			"Segments": [
				0,
				1,
				0,
				2.5,
				1
			]
		},
		{
			"Target": "Parameter",
			"Id": "Param_Angle_Rotation_1_ArtMesh29",
			"Segments": [
				0,
				0,
				1,
				0.222,
				0,
				0.444,
				3,
				0.667,
				3,
				1,
				1.278,
				3,
				1.889,
				0,
				2.5,
				0
			]
		},
		{
			"Target": "Parameter",
			"Id": "Param_Angle_Rotation_8_ArtMesh29",
			"Segments": [
				0,
				0,
				1,
				0.222,
				0,
				0.444,
				5,
				0.667,
				5,
				1,
				1.278,
				5,
				1.889,
				0,
				2.5,
				0
			]
		}
	]
}